math_verify/__init__.py
math_verify/errors.py
math_verify/few_shots.py
math_verify/grader.py
math_verify/metric.py
math_verify/parser.py
math_verify/tasks.py
math_verify/utils.py
math_verify-0.8.0.dist-info/licenses/LICENCE
math_verify-0.8.0.dist-info/METADATA
math_verify-0.8.0.dist-info/WHEEL
math_verify-0.8.0.dist-info/top_level.txt
math_verify-0.8.0.dist-info/RECORD
