Metadata-Version: 2.4
Name: math-verify
Version: 0.8.0
Summary: HuggingFace library for verifying mathematical answers
Author-email: Hynek Kydlíček <hynek.kydlicek@huggingface.co>
License: Apache 2.0
Project-URL: Repository, https://github.com/huggingface/math-verify
Keywords: verification,math,evaluation
Classifier: Intended Audience :: Developers
Classifier: Intended Audience :: Education
Classifier: Intended Audience :: Science/Research
Classifier: License :: OSI Approved :: Apache Software License
Classifier: Operating System :: OS Independent
Classifier: Programming Language :: Python :: 3
Classifier: Programming Language :: Python :: 3.10
Classifier: Programming Language :: Python :: 3.11
Classifier: Programming Language :: Python :: 3.12
Classifier: Topic :: Scientific/Engineering :: Artificial Intelligence
Requires-Python: >=3.10
License-File: LICENCE
Requires-Dist: latex2sympy2_extended==1.10.2
Provides-Extra: inference
Requires-Dist: lighteval[math]; extra == "inference"
Provides-Extra: test
Requires-Dist: pytest; extra == "test"
Provides-Extra: format
Requires-Dist: ruff; extra == "format"
Provides-Extra: dev
Requires-Dist: math-verify[test]; extra == "dev"
Requires-Dist: math-verify[format]; extra == "dev"
Provides-Extra: antlr4-9-3
Requires-Dist: latex2sympy2_extended[antlr4_9_3]; extra == "antlr4-9-3"
Provides-Extra: antlr4-11-0
Requires-Dist: latex2sympy2_extended[antlr4_11_0]; extra == "antlr4-11-0"
Provides-Extra: antlr4-13-2
Requires-Dist: latex2sympy2_extended[antlr4_13_2]; extra == "antlr4-13-2"
Dynamic: license-file
